metlink/__init__.py
metlink/cli.py
metlink/constants.py
metlink/metlink.py
tests/__init__.py
tests/test_metlink.py
metlink_python-0.1.0.dist-info/METADATA
metlink_python-0.1.0.dist-info/WHEEL
metlink_python-0.1.0.dist-info/top_level.txt
metlink_python-0.1.0.dist-info/RECORD
