Metadata-Version: 2.1
Name: metlink-python
Version: 0.1.0
Summary: API Wrapper and CLI for Metlink API
Author: Harry Ludemann
Author-email: 
Keywords: python,metlink,api,wrapper,cli
Classifier: Development Status :: 1 - Planning
Classifier: Intended Audience :: Developers
Classifier: Programming Language :: Python :: 3
Classifier: Operating System :: Unix
Classifier: Operating System :: MacOS :: MacOS X
Classifier: Operating System :: Microsoft :: Windows
Requires-Dist: urllib3
Requires-Dist: certifi
